{
  "13": ["אחד (Echad/One)", "אהבה (Ahava/Love)"],
  "18": ["חי (Chai/Life)"],
  "26": ["י-ה-ו-ה (The Name)"],
  "31": ["אל (God)"],
  "32": ["לב (Heart)", "כבוד (Honor)"],
  "45": ["אדם (Adam)", "גאולה (Redemption)"],
  "49": ["מזל טוב (Mazel Tov)", "לב טוב (Good Heart)"],
  "52": ["בן (Son)", "אליהו (Eliyahu)"],
  "61": ["אני (I am)", "אין (Nothingness)"],
  "65": ["אדני (Master)", "הלל (Praise)"],
  "70": ["יין (Wine)", "סוד (Secret)"],
  "72": ["חסד (Chesed/Kindness)"],
  "78": ["לחם (Bread)", "מזלא (Luck)"],
  "86": ["אלהים (God)", "הטבע (Nature)", "כוס (Cup)"],
  "91": ["אמן (Amen)", "מלאך (Angel)", "סוכה (Succah)"],
  "95": ["המלך (The King)", "דניאל (Daniel)"],
  "99": ["ידיד נפש (Yedid Nefesh)"],
  "130": ["סיני (Sinai)", "סולם (Ladder)"],
  "136": ["קול (Voice)", "ממון (Money)", "צום (Fast)"],
  "156": ["יוסף (Yosef)", "ציון (Zion)"],
  "207": ["אור (Light)", "רז (Secret)", "אין סוף (Infinite)"],
  "248": ["אברהם (Avraham)", "רמח (Limbs)"],
  "345": ["משה (Moshe/Moses)", "שילה (Shiloh)"],
  "358": ["משיח (Mashiach)", "נחש (Snake)"],
  "376": ["שלום (Peace)", "עשו (Esau)"],
  "395": ["נשמה (Soul)", "השמים (The Heavens)"],
  "400": ["ת (Tav)", "שקל (Shekel)"],
  "412": ["בית (Home)", "תאוה (Desire)"],
  "441": ["אמת (Truth)"],
  "496": ["מלכות (Malchut)", "לויתן (Leviathan)"],
  "500": ["פרו (Fruitful)"],
  "515": ["תפילה (Prayer)", "שירה (Song)"],
  "541": ["ישראל (Yisrael)"],
  "611": ["תורה (Torah)"],
  "613": ["תריג (Commandments)", "משה רבינו (Moshe Rabbeinu)"],
  "620": ["כתר (Crown)"],
  "913": ["בראשית (Bereshit)"],
  "14": ["דוד (David)", "יד (Hand)"],
  "333": ["שלג (Snow)"],
  "50": ["כל (All)", "ים (Sea)"],
  "19": ["חוה (Eve)"],
  "37": ["הבל (Abel)", "דגל (Flag)"],
  "58": ["נח (Noah)", "חן (Grace)"],
  "505": ["שרה (Sarah)"],
  "208": ["יצחק (Yitzchak)"],
  "307": ["רבקה (Rivka)"],
  "182": ["יעקב (Yaakov)"],
  "238": ["רחל (Rachel)"],
  "36": ["לאה (Leah)"],
  "256": ["אהרן (Aharon)"],
  "290": ["מרים (Miriam)"],
  "375": ["שלמה (Solomon)"],
  "337": ["שאול (Saul)"],
  "377": ["שמואל (Samuel)"],
  "661": ["אסתר (Esther)"],
  "274": ["מרדכי (Mordechai)"],
  "259": ["ראובן (Reuven)"],
  "466": ["שמעון (Shimon)"],
  "46": ["לוי (Levi)"],
  "30": ["יהודה (Yehuda)"],
  "830": ["יששכר (Issachar)"],
  "95": ["זבולון (Zevulun)"],
  "54": ["דן (Dan)"],
  "570": ["נפתלי (Naftali)"],
  "7": ["גד (Gad)"],
  "501": ["אשר (Asher)"],
  "162": ["בנימין (Benjamin)"],
  "331": ["אפרים (Ephraim)"],
  "395": ["מנשה (Menashe)"],
  "702": ["שבת (Shabbat)"],
  "861": ["ראש השנה (Rosh Hashanah)"],
  "304": ["יום כיפור (Yom Kippur)"],
  "486": ["סוכות (Sukkot)"],
  "1009": ["שמחת תורה (Simchat Torah)"],
  "89": ["חנוכה (Chanukah)"],
  "336": ["פורים (Purim)"],
  "148": ["פסח (Pesach)"],
  "778": ["שבועות (Shavuot)"],
  "513": ["ראש חודש (Rosh Chodesh)"],
  "776": ["תשעה באב (Tisha B'Av)"],
  "343": ["ל\"ג בעומר (Lag BaOmer)"],
  "141": ["מצוה (Mitzvah)"],
  "199": ["צדקה (Tzedakah)"],
  "713": ["תשובה (Teshuva)"],
  "216": ["גבורה (Gevurah)"],
  "1081": ["תפארת (Tiferet)"],
  "148": ["נצח (Netzach)"],
  "15": ["הוד (Hod)"],
  "80": ["יסוד (Yesod)"],
  "73": ["חכמה (Chochmah)"],
  "67": ["בינה (Binah)"],
  "474": ["דעת (Daat)"],
  "586": ["ירושלים (Jerusalem)"],
  "861": ["בית המקדש (The Temple)"],
  "177": ["גן עדן (Gan Eden)"],
  "108": ["גיהנום (Gehinnom)"],
  "149": ["עולם הבא (World to Come)"],
  "214": ["רוח (Spirit)"],
  "430": ["נפש (Soul/Nefesh)"],
  "385": ["שכינה (Shechinah)"],
  "86": ["הללויה (Hallelujah)"],
  "410": ["שמע (Shema)"],
  "910": ["תשרי (Tishrei)"],
  "364": ["חשון (Cheshvan)"],
  "116": ["כסלו (Kislev)"],
  "411": ["טבת (Tevet)"],
  "311": ["שבט (Shevat)"],
  "205": ["אדר (Adar)"],
  "170": ["ניסן (Nisan)"],
  "221": ["אייר (Iyar)"],
  "126": ["סיון (Sivan)"],
  "447": ["תמוז (Tammuz)"],
  "3": ["אב (Av)"],
  "67": ["אלול (Elul)"]
}